odoo/addons/pos_invoicing/README.rst
odoo/addons/pos_invoicing/__init__.py
odoo/addons/pos_invoicing/__manifest__.py
odoo/addons/pos_invoicing/i18n/ca.po
odoo/addons/pos_invoicing/i18n/ca_ES.po
odoo/addons/pos_invoicing/i18n/es.po
odoo/addons/pos_invoicing/i18n/fr.po
odoo/addons/pos_invoicing/i18n/pos_invoicing.pot
odoo/addons/pos_invoicing/i18n/pt.po
odoo/addons/pos_invoicing/models/__init__.py
odoo/addons/pos_invoicing/models/account_invoice.py
odoo/addons/pos_invoicing/models/account_payment.py
odoo/addons/pos_invoicing/models/pos_order.py
odoo/addons/pos_invoicing/models/pos_session.py
odoo/addons/pos_invoicing/readme/CONTRIBUTORS.rst
odoo/addons/pos_invoicing/readme/DESCRIPTION.rst
odoo/addons/pos_invoicing/static/description/account_invoice_form.png
odoo/addons/pos_invoicing/static/description/icon.png
odoo/addons/pos_invoicing/static/description/index.html
odoo/addons/pos_invoicing/tests/__init__.py
odoo/addons/pos_invoicing/tests/test_module.py
odoo/addons/pos_invoicing/views/view_account_invoice.xml
odoo12_addon_pos_invoicing-12.0.3.1.0.dist-info/METADATA
odoo12_addon_pos_invoicing-12.0.3.1.0.dist-info/WHEEL
odoo12_addon_pos_invoicing-12.0.3.1.0.dist-info/top_level.txt
odoo12_addon_pos_invoicing-12.0.3.1.0.dist-info/RECORD
